pytest_ringo
