Metadata-Version: 1.1
Name: pytest-ringo
Version: 0.2.1
Summary: pytest plugin to test webapplications using the Ringo webframework
Home-page: http://github.com/toirl/pytest-ringo/
Author: Torsten Irländer
Author-email: torsten.irlaender@googlemail.com
License: MIT
Platform: UNKNOWN
Classifier: Development Status :: 3 - Alpha
Classifier: Topic :: Software Development :: Testing
Classifier: Intended Audience :: Developers
Classifier: Operating System :: OS Independent
